srimutil_ccoverstreet/__main__.py
srimutil_ccoverstreet/ccosrimutil_gui.py
srimutil_ccoverstreet/chemicalparser.py
srimutil_ccoverstreet/cli.py
srimutil_ccoverstreet/layer_gui.py
srimutil_ccoverstreet/postprocess.py
srimutil_ccoverstreet/util_gui.py
srimutil_ccoverstreet/srim/SCOEF03.dat
srimutil_ccoverstreet/srim/SNUC03.dat
srimutil_ccoverstreet/srim/SRModule.exe
srimutil_ccoverstreet/srim/__init__.py
srimutil_ccoverstreet/srim/elements.py
srimutil_ccoverstreet/srim/make_elements.py
srimutil_ccoverstreet/srim/msvbvm50.dll
srimutil_ccoverstreet/srim/srimdriver.py
srimutil_ccoverstreet/srim/srimdriver_backup.py
srimutil_ccoverstreet-0.0.9.dist-info/licenses/LICENSE
srimutil_ccoverstreet-0.0.9.dist-info/METADATA
srimutil_ccoverstreet-0.0.9.dist-info/WHEEL
srimutil_ccoverstreet-0.0.9.dist-info/top_level.txt
srimutil_ccoverstreet-0.0.9.dist-info/RECORD
