Metadata-Version: 2.4
Name: srimutil_ccoverstreet
Version: 0.0.9
Summary: Python wrapper and GUI for running SRIM calculations
Author: Cale Overstreet
Requires-Python: >3.9
License-File: LICENSE
Requires-Dist: pillow
Requires-Dist: numpy
Requires-Dist: matplotlib
Requires-Dist: pyqt6
Requires-Dist: scipy
Dynamic: license-file
